explodify/Explodify.py
explodify/UnfoldDF.py
explodify/__init__.py
explodify-1.0.0.dist-info/LICENSE
explodify-1.0.0.dist-info/METADATA
explodify-1.0.0.dist-info/WHEEL
explodify-1.0.0.dist-info/entry_points.txt
explodify-1.0.0.dist-info/top_level.txt
explodify-1.0.0.dist-info/RECORD
